[{
    "id":"1",
    "phone":"13360435699",
    "email":"div@qq.com",
    "password":"11112222"
    },{
    "id":"2",
    "phone":"13360435680",
    "email":"haha@qq.com",
    "password":"1rerrtr2222"
    },{
    "id":"3",
    "phone":"15345678999",
    "email":"div@360.com",
    "password":"ggg12222"
    },{
    "id":"4",
    "phone":"18360435699",
    "password":"eref12222"
    },{
    "id":"5",
    "phone":"15860435699",
    "password":"11erwref222"
    },{
    "id":"6",
    "phone":"13560435699",
    "password":"111ffere22"
    },{
    "id":"7",
    "phone":"18860435699",
    "password":"rgghghtht"
    },{
    "id":"8",
    "phone":"17760435699",
    "password":"csddefee"
    },{
    "id":"9",
    "phone":"13360438799",
    "password":"11111111"
    }
]